{"cameraMode":{"drawMode":0,"name":"Shaded","section":"Shading Mode"},"sceneLighting":true,"audioPlay":false,"sceneViewState":{"m_AlwaysRefresh":false,"showFog":true,"showSkybox":true,"showFlares":true,"showImageEffects":true,"showParticleSystems":true,"showVisualEffectGraphs":true,"m_FxEnabled":true},"in2DMode":false,"pivot":{"x":252.20420837402345,"y":4.744812965393066,"z":2.6613411903381349},"rotation":{"x":0.011873959563672543,"y":-0.6947899460792542,"z":-0.01145519595593214,"w":-0.7189636826515198},"size":53.422943115234378,"orthographic":false}